snips_nlu_parsers/utils.py
snips_nlu_parsers/__init__.py
snips_nlu_parsers/builtin_entity_parser.py
snips_nlu_parsers/gazetteer_entity_parser.py
snips_nlu_parsers/__version__
snips_nlu_parsers/builtin_entities.py
snips_nlu_parsers/dylib/libsnips_nlu_parsers_rs.cpython-34m.so
snips_nlu_parsers/dylib/.gitignore
snips_nlu_parsers-0.4.3.dist-info/WHEEL
snips_nlu_parsers-0.4.3.dist-info/top_level.txt
snips_nlu_parsers-0.4.3.dist-info/METADATA
snips_nlu_parsers-0.4.3.dist-info/DESCRIPTION.rst
snips_nlu_parsers-0.4.3.dist-info/metadata.json
snips_nlu_parsers-0.4.3.dist-info/RECORD
