Metadata-Version: 2.0
Name: snips-nlu-parsers
Version: 0.4.3
Summary: Python wrapper of the snips-nlu-parsers Rust crate
Home-page: UNKNOWN
Author: Adrien Ball
Author-email: adrien.ball@snips.ai
License: Apache-2.0
Platform: UNKNOWN
Classifier: Programming Language :: Python :: 3
Classifier: Programming Language :: Python :: 3.5
Classifier: Programming Language :: Python :: 3.6
Classifier: Programming Language :: Python :: 3.7
Requires-Dist: future (<0.18,>=0.16)
Requires-Dist: pathlib (<2.0,>=1.0); python_version < "3.4"
